[
    {
        "snapshot_id": "1629566409",
        "altitude": "0",
        "heading": "194",
        "latitude": "34.56385",
        "longitude": "69.22348",
        "radar_id": "41187",
        "speed": "5",
        "squawk": "0000"
    },
    {
        "snapshot_id": "1629566418",
        "altitude": "0",
        "heading": "194",
        "latitude": "34.56350",
        "longitude": "69.22331",
        "radar_id": "41187",
        "speed": "7",
        "squawk": "0000"
    },
    {
        "snapshot_id": "1629566429",
        "altitude": "0",
        "heading": "188",
        "latitude": "34.56316",
        "longitude": "69.22331",
        "radar_id": "41187",
        "speed": "8",
        "squawk": "0000"
    },
    {
        "snapshot_id": "1629566439",
        "altitude": "0",
        "heading": "239",
        "latitude": "34.56299",
        "longitude": "69.22295",
        "radar_id": "41187",
        "speed": "5",
        "squawk": "0000"
    },
    {
        "snapshot_id": "1629566449",
        "altitude": "0",
        "heading": "289",
        "latitude": "34.56316",
        "longitude": "69.22263",
        "radar_id": "41187",
        "speed": "7",
        "squawk": "0000"
    },
    {
        "snapshot_id": "1629566456",
        "altitude": "0",
        "heading": "286",
        "latitude": "34.56316",
        "longitude": "69.22226",
        "radar_id": "41187",
        "speed": "18",
        "squawk": "0442"
    },
    {
        "snapshot_id": "1629566459",
        "altitude": "0",
        "heading": "286",
        "latitude": "34.56333",
        "longitude": "69.22192",
        "radar_id": "41187",
        "speed": "32",
        "squawk": "0442"
    },
    {
        "snapshot_id": "1629566461",
        "altitude": "0",
        "heading": "286",
        "latitude": "34.56334",
        "longitude": "69.22139",
        "radar_id": "41187",
        "speed": "42",
        "squawk": "0442"
    },
    {
        "snapshot_id": "1629566463",
        "altitude": "0",
        "heading": "286",
        "latitude": "34.56352",
        "longitude": "69.22086",
        "radar_id": "41187",
        "speed": "52",
        "squawk": "0442"
    },
    {
        "snapshot_id": "1629566464",
        "altitude": "0",
        "heading": "286",
        "latitude": "34.56369",
        "longitude": "69.22053",
        "radar_id": "41187",
        "speed": "57",
        "squawk": "0442"
    },
    {
        "snapshot_id": "1629566466",
        "altitude": "0",
        "heading": "286",
        "latitude": "34.56386",
        "longitude": "69.22002",
        "radar_id": "41187",
        "speed": "65",
        "squawk": "0442"
    },
    {
        "snapshot_id": "1629566467",
        "altitude": "0",
        "heading": "286",
        "latitude": "34.56386",
        "longitude": "69.21967",
        "radar_id": "41187",
        "speed": "69",
        "squawk": "0442"
    },
    {
        "snapshot_id": "1629566469",
        "altitude": "0",
        "heading": "286",
        "latitude": "34.56420",
        "longitude": "69.21864",
        "radar_id": "41187",
        "speed": "80",
        "squawk": "0442"
    },
    {
        "snapshot_id": "1629566470",
        "altitude": "0",
        "heading": "286",
        "latitude": "34.56420",
        "longitude": "69.21812",
        "radar_id": "41187",
        "speed": "84",
        "squawk": "0442"
    },
    {
        "snapshot_id": "1629566471",
        "altitude": "0",
        "heading": "286",
        "latitude": "34.56437",
        "longitude": "69.21776",
        "radar_id": "41187",
        "speed": "88",
        "squawk": "0442"
    },
    {
        "snapshot_id": "1629566482",
        "altitude": "5750",
        "heading": "287",
        "latitude": "34.56592",
        "longitude": "69.21158",
        "radar_id": "41187",
        "speed": "125",
        "squawk": "0442"
    },
    {
        "snapshot_id": "1629566495",
        "altitude": "5875",
        "heading": "286",
        "latitude": "34.56848",
        "longitude": "69.20159",
        "radar_id": "41187",
        "speed": "151",
        "squawk": "0442"
    },
    {
        "snapshot_id": "1629566511",
        "altitude": "6100",
        "heading": "287",
        "latitude": "34.57196",
        "longitude": "69.18803",
        "radar_id": "41187",
        "speed": "162",
        "squawk": "0442"
    },
    {
        "snapshot_id": "1629566524",
        "altitude": "6375",
        "heading": "287",
        "latitude": "34.57521",
        "longitude": "69.17580",
        "radar_id": "41187",
        "speed": "172",
        "squawk": "0442"
    },
    {
        "snapshot_id": "1629566537",
        "altitude": "6600",
        "heading": "290",
        "latitude": "34.57881",
        "longitude": "69.16328",
        "radar_id": "41187",
        "speed": "185",
        "squawk": "0442"
    },
    {
        "snapshot_id": "1629566553",
        "altitude": "6925",
        "heading": "296",
        "latitude": "34.58431",
        "longitude": "69.14766",
        "radar_id": "41187",
        "speed": "193",
        "squawk": "0442"
    },
    {
        "snapshot_id": "1629566557",
        "altitude": "7000",
        "heading": "301",
        "latitude": "34.58588",
        "longitude": "69.14442",
        "radar_id": "41187",
        "speed": "195",
        "squawk": "0442"
    },
    {
        "snapshot_id": "1629566563",
        "altitude": "7150",
        "heading": "315",
        "latitude": "34.58935",
        "longitude": "69.13909",
        "radar_id": "41187",
        "speed": "195",
        "squawk": "0442"
    },
    {
        "snapshot_id": "1629566566",
        "altitude": "7250",
        "heading": "323",
        "latitude": "34.59169",
        "longitude": "69.13657",
        "radar_id": "41187",
        "speed": "196",
        "squawk": "0442"
    },
    {
        "snapshot_id": "1629566570",
        "altitude": "7350",
        "heading": "332",
        "latitude": "34.59464",
        "longitude": "69.13451",
        "radar_id": "41187",
        "speed": "197",
        "squawk": "0442"
    },
    {
        "snapshot_id": "1629566573",
        "altitude": "7400",
        "heading": "340",
        "latitude": "34.59709",
        "longitude": "69.13332",
        "radar_id": "41187",
        "speed": "197",
        "squawk": "0442"
    },
    {
        "snapshot_id": "1629566577",
        "altitude": "7475",
        "heading": "349",
        "latitude": "34.60030",
        "longitude": "69.13231",
        "radar_id": "41187",
        "speed": "199",
        "squawk": "0442"
    },
    {
        "snapshot_id": "1629566580",
        "altitude": "7550",
        "heading": "357",
        "latitude": "34.60326",
        "longitude": "69.13216",
        "radar_id": "41187",
        "speed": "200",
        "squawk": "0442"
    },
    {
        "snapshot_id": "1629566586",
        "altitude": "7650",
        "heading": "13",
        "latitude": "34.60894",
        "longitude": "69.13307",
        "radar_id": "41187",
        "speed": "202",
        "squawk": "0442"
    },
    {
        "snapshot_id": "1629566590",
        "altitude": "7650",
        "heading": "25",
        "latitude": "34.61266",
        "longitude": "69.13479",
        "radar_id": "41187",
        "speed": "208",
        "squawk": "0442"
    },
    {
        "snapshot_id": "1629566594",
        "altitude": "7650",
        "heading": "36",
        "latitude": "34.61541",
        "longitude": "69.13685",
        "radar_id": "41187",
        "speed": "211",
        "squawk": "0442"
    },
    {
        "snapshot_id": "1629566596",
        "altitude": "7625",
        "heading": "41",
        "latitude": "34.61765",
        "longitude": "69.13926",
        "radar_id": "41187",
        "speed": "214",
        "squawk": "0442"
    },
    {
        "snapshot_id": "1629566604",
        "altitude": "7650",
        "heading": "68",
        "latitude": "34.62136",
        "longitude": "69.14669",
        "radar_id": "41187",
        "speed": "219",
        "squawk": "0442"
    },
    {
        "snapshot_id": "1629566607",
        "altitude": "7650",
        "heading": "78",
        "latitude": "34.62222",
        "longitude": "69.15064",
        "radar_id": "41187",
        "speed": "221",
        "squawk": "0442"
    },
    {
        "snapshot_id": "1629566614",
        "altitude": "7650",
        "heading": "95",
        "latitude": "34.62236",
        "longitude": "69.15905",
        "radar_id": "41187",
        "speed": "227",
        "squawk": "0442"
    },
    {
        "snapshot_id": "1629566617",
        "altitude": "7650",
        "heading": "101",
        "latitude": "34.62183",
        "longitude": "69.16283",
        "radar_id": "41187",
        "speed": "229",
        "squawk": "0442"
    },
    {
        "snapshot_id": "1629566620",
        "altitude": "7675",
        "heading": "106",
        "latitude": "34.62099",
        "longitude": "69.16678",
        "radar_id": "41187",
        "speed": "231",
        "squawk": "0442"
    },
    {
        "snapshot_id": "1629566627",
        "altitude": "7675",
        "heading": "109",
        "latitude": "34.61871",
        "longitude": "69.17525",
        "radar_id": "41187",
        "speed": "237",
        "squawk": "0442"
    },
    {
        "snapshot_id": "1629566630",
        "altitude": "7675",
        "heading": "109",
        "latitude": "34.61736",
        "longitude": "69.17947",
        "radar_id": "41187",
        "speed": "239",
        "squawk": "0442"
    },
    {
        "snapshot_id": "1629566633",
        "altitude": "7700",
        "heading": "110",
        "latitude": "34.61618",
        "longitude": "69.18394",
        "radar_id": "41187",
        "speed": "242",
        "squawk": "0442"
    },
    {
        "snapshot_id": "1629566640",
        "altitude": "7725",
        "heading": "110",
        "latitude": "34.61359",
        "longitude": "69.19183",
        "radar_id": "41187",
        "speed": "245",
        "squawk": "0442"
    },
    {
        "snapshot_id": "1629566643",
        "altitude": "7750",
        "heading": "110",
        "latitude": "34.61224",
        "longitude": "69.19627",
        "radar_id": "41187",
        "speed": "247",
        "squawk": "0442"
    },
    {
        "snapshot_id": "1629566663",
        "altitude": "7825",
        "heading": "110",
        "latitude": "34.60414",
        "longitude": "69.22261",
        "radar_id": "41187",
        "speed": "257",
        "squawk": "0442"
    },
    {
        "snapshot_id": "1629566679",
        "altitude": "7825",
        "heading": "116",
        "latitude": "34.59640",
        "longitude": "69.24442",
        "radar_id": "41187",
        "speed": "266",
        "squawk": "0442"
    },
    {
        "snapshot_id": "1629566692",
        "altitude": "8550",
        "heading": "119",
        "latitude": "34.58887",
        "longitude": "69.26118",
        "radar_id": "41187",
        "speed": "241",
        "squawk": "0442"
    },
    {
        "snapshot_id": "1629566705",
        "altitude": "9425",
        "heading": "129",
        "latitude": "34.58180",
        "longitude": "69.27451",
        "radar_id": "41187",
        "speed": "215",
        "squawk": "0442"
    },
    {
        "snapshot_id": "1629566708",
        "altitude": "9550",
        "heading": "133",
        "latitude": "34.57989",
        "longitude": "69.27715",
        "radar_id": "41187",
        "speed": "215",
        "squawk": "0442"
    },
    {
        "snapshot_id": "1629566711",
        "altitude": "9650",
        "heading": "138",
        "latitude": "34.57768",
        "longitude": "69.27934",
        "radar_id": "41187",
        "speed": "214",
        "squawk": "0442"
    },
    {
        "snapshot_id": "1629566715",
        "altitude": "9750",
        "heading": "147",
        "latitude": "34.57462",
        "longitude": "69.28225",
        "radar_id": "41187",
        "speed": "214",
        "squawk": "0442"
    },
    {
        "snapshot_id": "1629566721",
        "altitude": "9875",
        "heading": "160",
        "latitude": "34.56871",
        "longitude": "69.28567",
        "radar_id": "41187",
        "speed": "217",
        "squawk": "0442"
    },
    {
        "snapshot_id": "1629566724",
        "altitude": "9950",
        "heading": "162",
        "latitude": "34.56583",
        "longitude": "69.28665",
        "radar_id": "41187",
        "speed": "217",
        "squawk": "0442"
    },
    {
        "snapshot_id": "1629566728",
        "altitude": "10025",
        "heading": "174",
        "latitude": "34.56173",
        "longitude": "69.28751",
        "radar_id": "41187",
        "speed": "220",
        "squawk": "0442"
    },
    {
        "snapshot_id": "1629566732",
        "altitude": "10125",
        "heading": "182",
        "latitude": "34.55777",
        "longitude": "69.28751",
        "radar_id": "41187",
        "speed": "220",
        "squawk": "0442"
    },
    {
        "snapshot_id": "1629566736",
        "altitude": "10200",
        "heading": "190",
        "latitude": "34.55410",
        "longitude": "69.28694",
        "radar_id": "41187",
        "speed": "219",
        "squawk": "0442"
    },
    {
        "snapshot_id": "1629566739",
        "altitude": "10300",
        "heading": "196",
        "latitude": "34.55084",
        "longitude": "69.28590",
        "radar_id": "41187",
        "speed": "218",
        "squawk": "0442"
    },
    {
        "snapshot_id": "1629566742",
        "altitude": "10400",
        "heading": "203",
        "latitude": "34.54793",
        "longitude": "69.28438",
        "radar_id": "41187",
        "speed": "217",
        "squawk": "0442"
    },
    {
        "snapshot_id": "1629566746",
        "altitude": "10500",
        "heading": "213",
        "latitude": "34.54488",
        "longitude": "69.28230",
        "radar_id": "41187",
        "speed": "215",
        "squawk": "0442"
    },
    {
        "snapshot_id": "1629566749",
        "altitude": "10575",
        "heading": "219",
        "latitude": "34.54232",
        "longitude": "69.27990",
        "radar_id": "41187",
        "speed": "215",
        "squawk": "0442"
    },
    {
        "snapshot_id": "1629566752",
        "altitude": "10625",
        "heading": "227",
        "latitude": "34.53992",
        "longitude": "69.27692",
        "radar_id": "41187",
        "speed": "216",
        "squawk": "0442"
    },
    {
        "snapshot_id": "1629566762",
        "altitude": "10875",
        "heading": "249",
        "latitude": "34.53497",
        "longitude": "69.26650",
        "radar_id": "41187",
        "speed": "213",
        "squawk": "0442"
    },
    {
        "snapshot_id": "1629566772",
        "altitude": "11200",
        "heading": "259",
        "latitude": "34.53278",
        "longitude": "69.25562",
        "radar_id": "41187",
        "speed": "207",
        "squawk": "0442"
    },
    {
        "snapshot_id": "1629566776",
        "altitude": "11325",
        "heading": "259",
        "latitude": "34.53209",
        "longitude": "69.25148",
        "radar_id": "41187",
        "speed": "207",
        "squawk": "0442"
    },
    {
        "snapshot_id": "1629566783",
        "altitude": "11525",
        "heading": "261",
        "latitude": "34.53124",
        "longitude": "69.24333",
        "radar_id": "41187",
        "speed": "205",
        "squawk": "0442"
    },
    {
        "snapshot_id": "1629566787",
        "altitude": "11650",
        "heading": "261",
        "latitude": "34.53054",
        "longitude": "69.23865",
        "radar_id": "41187",
        "speed": "205",
        "squawk": "0442"
    },
    {
        "snapshot_id": "1629566790",
        "altitude": "11725",
        "heading": "262",
        "latitude": "34.53021",
        "longitude": "69.23522",
        "radar_id": "41187",
        "speed": "203",
        "squawk": "0442"
    },
    {
        "snapshot_id": "1629566802",
        "altitude": "12100",
        "heading": "262",
        "latitude": "34.52866",
        "longitude": "69.22127",
        "radar_id": "41187",
        "speed": "200",
        "squawk": "0442"
    },
    {
        "snapshot_id": "1629566834",
        "altitude": "12750",
        "heading": "256",
        "latitude": "34.52295",
        "longitude": "69.18578",
        "radar_id": "41187",
        "speed": "209",
        "squawk": "0442"
    },
    {
        "snapshot_id": "1629566867",
        "altitude": "12925",
        "heading": "229",
        "latitude": "34.51108",
        "longitude": "69.14649",
        "radar_id": "41187",
        "speed": "246",
        "squawk": "0442"
    },
    {
        "snapshot_id": "1629566873",
        "altitude": "12900",
        "heading": "216",
        "latitude": "34.50572",
        "longitude": "69.14061",
        "radar_id": "41187",
        "speed": "255",
        "squawk": "0442"
    },
    {
        "snapshot_id": "1629566880",
        "altitude": "12900",
        "heading": "212",
        "latitude": "34.49916",
        "longitude": "69.13547",
        "radar_id": "41187",
        "speed": "261",
        "squawk": "0442"
    },
    {
        "snapshot_id": "1629566883",
        "altitude": "12900",
        "heading": "212",
        "latitude": "34.49597",
        "longitude": "69.13315",
        "radar_id": "41187",
        "speed": "263",
        "squawk": "0442"
    },
    {
        "snapshot_id": "1629566915",
        "altitude": "12950",
        "heading": "210",
        "latitude": "34.46077",
        "longitude": "69.10737",
        "radar_id": "41187",
        "speed": "284",
        "squawk": "0442"
    },
    {
        "snapshot_id": "1629566946",
        "altitude": "12850",
        "heading": "211",
        "latitude": "34.42482",
        "longitude": "69.08106",
        "radar_id": "41187",
        "speed": "289",
        "squawk": "0442"
    },
    {
        "snapshot_id": "1629566978",
        "altitude": "12875",
        "heading": "212",
        "latitude": "34.38898",
        "longitude": "69.05308",
        "radar_id": "41187",
        "speed": "289",
        "squawk": "0442"
    },
    {
        "snapshot_id": "1629567010",
        "altitude": "13525",
        "heading": "211",
        "latitude": "34.35276",
        "longitude": "69.02561",
        "radar_id": "41187",
        "speed": "277",
        "squawk": "0442"
    },
    {
        "snapshot_id": "1629567042",
        "altitude": "14625",
        "heading": "212",
        "latitude": "34.31985",
        "longitude": "69.00078",
        "radar_id": "41187",
        "speed": "254",
        "squawk": "0442"
    },
    {
        "snapshot_id": "1629567074",
        "altitude": "15725",
        "heading": "212",
        "latitude": "34.28931",
        "longitude": "68.97743",
        "radar_id": "41187",
        "speed": "233",
        "squawk": "0442"
    },
    {
        "snapshot_id": "1629567113",
        "altitude": "16000",
        "heading": "211",
        "latitude": "34.25217",
        "longitude": "68.94958",
        "radar_id": "41187",
        "speed": "259",
        "squawk": "0442"
    },
    {
        "snapshot_id": "1629567144",
        "altitude": "16050",
        "heading": "213",
        "latitude": "34.21816",
        "longitude": "68.92385",
        "radar_id": "41187",
        "speed": "280",
        "squawk": "0442"
    },
    {
        "snapshot_id": "1629567180",
        "altitude": "16000",
        "heading": "211",
        "latitude": "34.17763",
        "longitude": "68.89291",
        "radar_id": "41187",
        "speed": "300",
        "squawk": "0442"
    },
    {
        "snapshot_id": "1629567211",
        "altitude": "16000",
        "heading": "212",
        "latitude": "34.13987",
        "longitude": "68.86425",
        "radar_id": "41187",
        "speed": "309",
        "squawk": "0442"
    },
    {
        "snapshot_id": "1629567218",
        "altitude": "16000",
        "heading": "212",
        "latitude": "34.13168",
        "longitude": "68.85793",
        "radar_id": "41187",
        "speed": "308",
        "squawk": "0442"
    },
    {
        "snapshot_id": "1629567377",
        "altitude": "18150",
        "heading": "264",
        "latitude": "33.97417",
        "longitude": "68.68753",
        "radar_id": "41187",
        "speed": "269",
        "squawk": "0442"
    },
    {
        "snapshot_id": "1629567443",
        "altitude": "20125",
        "heading": "272",
        "latitude": "33.97503",
        "longitude": "68.59595",
        "radar_id": "41187",
        "speed": "230",
        "squawk": "0442"
    },
    {
        "snapshot_id": "1629567506",
        "altitude": "21025",
        "heading": "269",
        "latitude": "33.97554",
        "longitude": "68.51578",
        "radar_id": "41187",
        "speed": "241",
        "squawk": "0442"
    },
    {
        "snapshot_id": "1629567525",
        "altitude": "21050",
        "heading": "268",
        "latitude": "33.97522",
        "longitude": "68.48911",
        "radar_id": "41187",
        "speed": "254",
        "squawk": "0442"
    },
    {
        "snapshot_id": "1629570552",
        "altitude": "22975",
        "heading": "208",
        "latitude": "30.61963",
        "longitude": "65.08053",
        "radar_id": "4007",
        "speed": "278",
        "squawk": "0000"
    },
    {
        "snapshot_id": "1629570613",
        "altitude": "23875",
        "heading": "208",
        "latitude": "30.55238",
        "longitude": "65.03815",
        "radar_id": "4007",
        "speed": "264",
        "squawk": "0442"
    },
    {
        "snapshot_id": "1629570674",
        "altitude": "24500",
        "heading": "208",
        "latitude": "30.48747",
        "longitude": "64.99727",
        "radar_id": "4007",
        "speed": "264",
        "squawk": "0442"
    },
    {
        "snapshot_id": "1629570738",
        "altitude": "24525",
        "heading": "208",
        "latitude": "30.41551",
        "longitude": "64.95177",
        "radar_id": "4007",
        "speed": "286",
        "squawk": "0442"
    },
    {
        "snapshot_id": "1629570802",
        "altitude": "24500",
        "heading": "208",
        "latitude": "30.33861",
        "longitude": "64.90333",
        "radar_id": "4007",
        "speed": "302",
        "squawk": "0442"
    },
    {
        "snapshot_id": "1629570869",
        "altitude": "24500",
        "heading": "209",
        "latitude": "30.25552",
        "longitude": "64.85030",
        "radar_id": "4007",
        "speed": "311",
        "squawk": "0442"
    },
    {
        "snapshot_id": "1629570935",
        "altitude": "24500",
        "heading": "208",
        "latitude": "30.17139",
        "longitude": "64.79694",
        "radar_id": "4007",
        "speed": "317",
        "squawk": "0442"
    },
    {
        "snapshot_id": "1629570998",
        "altitude": "24500",
        "heading": "208",
        "latitude": "30.08958",
        "longitude": "64.74496",
        "radar_id": "4007",
        "speed": "320",
        "squawk": "0442"
    },
    {
        "snapshot_id": "1629571058",
        "altitude": "24500",
        "heading": "209",
        "latitude": "30.01071",
        "longitude": "64.69493",
        "radar_id": "4007",
        "speed": "323",
        "squawk": "0442"
    },
    {
        "snapshot_id": "1629571122",
        "altitude": "24500",
        "heading": "209",
        "latitude": "29.92788",
        "longitude": "64.64180",
        "radar_id": "4007",
        "speed": "324",
        "squawk": "0442"
    },
    {
        "snapshot_id": "1629571184",
        "altitude": "24500",
        "heading": "209",
        "latitude": "29.84528",
        "longitude": "64.58873",
        "radar_id": "4007",
        "speed": "324",
        "squawk": "0442"
    },
    {
        "snapshot_id": "1629571247",
        "altitude": "24500",
        "heading": "209",
        "latitude": "29.76308",
        "longitude": "64.53584",
        "radar_id": "4007",
        "speed": "325",
        "squawk": "0442"
    },
    {
        "snapshot_id": "1629571310",
        "altitude": "24500",
        "heading": "209",
        "latitude": "29.68007",
        "longitude": "64.48241",
        "radar_id": "4007",
        "speed": "326",
        "squawk": "0442"
    },
    {
        "snapshot_id": "1629571373",
        "altitude": "24500",
        "heading": "200",
        "latitude": "29.59296",
        "longitude": "64.43720",
        "radar_id": "4007",
        "speed": "328",
        "squawk": "0442"
    },
    {
        "snapshot_id": "1629571434",
        "altitude": "24500",
        "heading": "203",
        "latitude": "29.50816",
        "longitude": "64.39631",
        "radar_id": "4007",
        "speed": "328",
        "squawk": "0442"
    },
    {
        "snapshot_id": "1629571494",
        "altitude": "24175",
        "heading": "202",
        "latitude": "29.42208",
        "longitude": "64.35527",
        "radar_id": "4007",
        "speed": "338",
        "squawk": "0442"
    },
    {
        "snapshot_id": "1629571557",
        "altitude": "23525",
        "heading": "202",
        "latitude": "29.32782",
        "longitude": "64.31095",
        "radar_id": "4007",
        "speed": "354",
        "squawk": "0442"
    },
    {
        "snapshot_id": "1629571620",
        "altitude": "23500",
        "heading": "202",
        "latitude": "29.23364",
        "longitude": "64.26668",
        "radar_id": "4007",
        "speed": "341",
        "squawk": "0442"
    },
    {
        "snapshot_id": "1629571668",
        "altitude": "23500",
        "heading": "192",
        "latitude": "29.16215",
        "longitude": "64.23838",
        "radar_id": "4007",
        "speed": "337",
        "squawk": "0442"
    },
    {
        "snapshot_id": "1629571671",
        "altitude": "23500",
        "heading": "191",
        "latitude": "29.15753",
        "longitude": "64.23717",
        "radar_id": "4007",
        "speed": "336",
        "squawk": "0442"
    },
    {
        "snapshot_id": "1629571738",
        "altitude": "23500",
        "heading": "191",
        "latitude": "29.05674",
        "longitude": "64.21487",
        "radar_id": "4007",
        "speed": "331",
        "squawk": "0442"
    },
    {
        "snapshot_id": "1629571788",
        "altitude": "23500",
        "heading": "190",
        "latitude": "28.98079",
        "longitude": "64.19808",
        "radar_id": "4007",
        "speed": "330",
        "squawk": "0442"
    },
    {
        "snapshot_id": "1629571834",
        "altitude": "23500",
        "heading": "191",
        "latitude": "28.91299",
        "longitude": "64.18314",
        "radar_id": "41051",
        "speed": "328",
        "squawk": "0442"
    },
    {
        "snapshot_id": "1629571920",
        "altitude": "23525",
        "heading": "190",
        "latitude": "28.78348",
        "longitude": "64.15461",
        "radar_id": "41051",
        "speed": "328",
        "squawk": "0442"
    },
    {
        "snapshot_id": "1629571982",
        "altitude": "23500",
        "heading": "190",
        "latitude": "28.68973",
        "longitude": "64.13403",
        "radar_id": "41051",
        "speed": "336",
        "squawk": "0442"
    },
    {
        "snapshot_id": "1629572044",
        "altitude": "23500",
        "heading": "191",
        "latitude": "28.59532",
        "longitude": "64.11309",
        "radar_id": "41051",
        "speed": "338",
        "squawk": "0442"
    },
    {
        "snapshot_id": "1629572105",
        "altitude": "23500",
        "heading": "190",
        "latitude": "28.50030",
        "longitude": "64.09230",
        "radar_id": "41051",
        "speed": "338",
        "squawk": "0442"
    },
    {
        "snapshot_id": "1629572167",
        "altitude": "23500",
        "heading": "190",
        "latitude": "28.40625",
        "longitude": "64.07158",
        "radar_id": "41051",
        "speed": "338",
        "squawk": "0442"
    },
    {
        "snapshot_id": "1629572227",
        "altitude": "23500",
        "heading": "190",
        "latitude": "28.31296",
        "longitude": "64.05109",
        "radar_id": "41051",
        "speed": "337",
        "squawk": "0442"
    },
    {
        "snapshot_id": "1629572289",
        "altitude": "23500",
        "heading": "190",
        "latitude": "28.21870",
        "longitude": "64.03070",
        "radar_id": "41051",
        "speed": "337",
        "squawk": "0442"
    },
    {
        "snapshot_id": "1629572352",
        "altitude": "23500",
        "heading": "190",
        "latitude": "28.12188",
        "longitude": "64.00958",
        "radar_id": "41051",
        "speed": "336",
        "squawk": "0442"
    },
    {
        "snapshot_id": "1629572416",
        "altitude": "23500",
        "heading": "190",
        "latitude": "28.02379",
        "longitude": "63.98850",
        "radar_id": "41051",
        "speed": "335",
        "squawk": "0442"
    },
    {
        "snapshot_id": "1629572477",
        "altitude": "23500",
        "heading": "190",
        "latitude": "27.93013",
        "longitude": "63.96821",
        "radar_id": "41051",
        "speed": "335",
        "squawk": "0442"
    },
    {
        "snapshot_id": "1629572538",
        "altitude": "23500",
        "heading": "190",
        "latitude": "27.83711",
        "longitude": "63.94794",
        "radar_id": "41051",
        "speed": "337",
        "squawk": "0442"
    },
    {
        "snapshot_id": "1629572598",
        "altitude": "23500",
        "heading": "190",
        "latitude": "27.74425",
        "longitude": "63.92786",
        "radar_id": "41051",
        "speed": "338",
        "squawk": "0442"
    },
    {
        "snapshot_id": "1629572659",
        "altitude": "23500",
        "heading": "190",
        "latitude": "27.65035",
        "longitude": "63.90763",
        "radar_id": "41051",
        "speed": "338",
        "squawk": "0442"
    },
    {
        "snapshot_id": "1629572720",
        "altitude": "23500",
        "heading": "190",
        "latitude": "27.55697",
        "longitude": "63.88735",
        "radar_id": "41051",
        "speed": "338",
        "squawk": "0442"
    },
    {
        "snapshot_id": "1629572784",
        "altitude": "23500",
        "heading": "190",
        "latitude": "27.45842",
        "longitude": "63.86606",
        "radar_id": "41051",
        "speed": "338",
        "squawk": "0442"
    },
    {
        "snapshot_id": "1629572845",
        "altitude": "23500",
        "heading": "190",
        "latitude": "27.36452",
        "longitude": "63.84596",
        "radar_id": "41051",
        "speed": "338",
        "squawk": "0442"
    },
    {
        "snapshot_id": "1629572906",
        "altitude": "23500",
        "heading": "191",
        "latitude": "27.27086",
        "longitude": "63.82576",
        "radar_id": "41051",
        "speed": "340",
        "squawk": "0442"
    },
    {
        "snapshot_id": "1629572970",
        "altitude": "23500",
        "heading": "190",
        "latitude": "27.17166",
        "longitude": "63.80429",
        "radar_id": "41051",
        "speed": "339",
        "squawk": "0442"
    },
    {
        "snapshot_id": "1629573030",
        "altitude": "23500",
        "heading": "190",
        "latitude": "27.07910",
        "longitude": "63.78455",
        "radar_id": "41051",
        "speed": "338",
        "squawk": "0442"
    },
    {
        "snapshot_id": "1629573073",
        "altitude": "23500",
        "heading": "201",
        "latitude": "27.01332",
        "longitude": "63.76765",
        "radar_id": "41051",
        "speed": "340",
        "squawk": "0442"
    },
    {
        "snapshot_id": "1629573079",
        "altitude": "23500",
        "heading": "205",
        "latitude": "27.00412",
        "longitude": "63.76320",
        "radar_id": "41051",
        "speed": "339",
        "squawk": "0442"
    },
    {
        "snapshot_id": "1629573085",
        "altitude": "23500",
        "heading": "209",
        "latitude": "26.99588",
        "longitude": "63.75838",
        "radar_id": "41051",
        "speed": "339",
        "squawk": "0442"
    },
    {
        "snapshot_id": "1629573146",
        "altitude": "23500",
        "heading": "214",
        "latitude": "26.91669",
        "longitude": "63.69878",
        "radar_id": "41051",
        "speed": "341",
        "squawk": "0442"
    },
    {
        "snapshot_id": "1629573207",
        "altitude": "23500",
        "heading": "214",
        "latitude": "26.83639",
        "longitude": "63.63789",
        "radar_id": "41051",
        "speed": "339",
        "squawk": "0442"
    },
    {
        "snapshot_id": "1629573231",
        "altitude": "23500",
        "heading": "214",
        "latitude": "26.80464",
        "longitude": "63.61385",
        "radar_id": "41051",
        "speed": "340",
        "squawk": "0442"
    },
    {
        "snapshot_id": "1629573319",
        "altitude": "23500",
        "heading": "214",
        "latitude": "26.68932",
        "longitude": "63.52684",
        "radar_id": "42251",
        "speed": "339",
        "squawk": "0442"
    },
    {
        "snapshot_id": "1629573384",
        "altitude": "23500",
        "heading": "213",
        "latitude": "26.60587",
        "longitude": "63.46449",
        "radar_id": "42251",
        "speed": "340",
        "squawk": "0442"
    },
    {
        "snapshot_id": "1629573445",
        "altitude": "23500",
        "heading": "213",
        "latitude": "26.52562",
        "longitude": "63.40402",
        "radar_id": "42251",
        "speed": "340",
        "squawk": "0442"
    },
    {
        "snapshot_id": "1629573507",
        "altitude": "23500",
        "heading": "214",
        "latitude": "26.44451",
        "longitude": "63.34331",
        "radar_id": "41051",
        "speed": "341",
        "squawk": "0442"
    },
    {
        "snapshot_id": "1629573568",
        "altitude": "23500",
        "heading": "214",
        "latitude": "26.36519",
        "longitude": "63.28373",
        "radar_id": "41051",
        "speed": "340",
        "squawk": "0442"
    },
    {
        "snapshot_id": "1629573629",
        "altitude": "23500",
        "heading": "214",
        "latitude": "26.28502",
        "longitude": "63.22368",
        "radar_id": "41051",
        "speed": "341",
        "squawk": "0442"
    },
    {
        "snapshot_id": "1629573690",
        "altitude": "23500",
        "heading": "214",
        "latitude": "26.20505",
        "longitude": "63.16392",
        "radar_id": "41051",
        "speed": "342",
        "squawk": "0442"
    },
    {
        "snapshot_id": "1629573750",
        "altitude": "23500",
        "heading": "214",
        "latitude": "26.12462",
        "longitude": "63.10397",
        "radar_id": "41051",
        "speed": "345",
        "squawk": "0442"
    },
    {
        "snapshot_id": "1629573811",
        "altitude": "23500",
        "heading": "213",
        "latitude": "26.04369",
        "longitude": "63.04359",
        "radar_id": "41051",
        "speed": "346",
        "squawk": "0442"
    },
    {
        "snapshot_id": "1629573877",
        "altitude": "23500",
        "heading": "213",
        "latitude": "25.95520",
        "longitude": "62.97778",
        "radar_id": "41051",
        "speed": "348",
        "squawk": "0442"
    },
    {
        "snapshot_id": "1629573941",
        "altitude": "23500",
        "heading": "213",
        "latitude": "25.87006",
        "longitude": "62.91461",
        "radar_id": "42251",
        "speed": "349",
        "squawk": "0442"
    },
    {
        "snapshot_id": "1629574002",
        "altitude": "23500",
        "heading": "213",
        "latitude": "25.78789",
        "longitude": "62.85375",
        "radar_id": "42251",
        "speed": "350",
        "squawk": "0442"
    },
    {
        "snapshot_id": "1629574064",
        "altitude": "23500",
        "heading": "213",
        "latitude": "25.70321",
        "longitude": "62.79122",
        "radar_id": "41051",
        "speed": "351",
        "squawk": "0442"
    },
    {
        "snapshot_id": "1629574128",
        "altitude": "23500",
        "heading": "213",
        "latitude": "25.61737",
        "longitude": "62.72786",
        "radar_id": "42251",
        "speed": "351",
        "squawk": "0442"
    },
    {
        "snapshot_id": "1629574192",
        "altitude": "23500",
        "heading": "213",
        "latitude": "25.53017",
        "longitude": "62.66332",
        "radar_id": "41051",
        "speed": "352",
        "squawk": "0442"
    },
    {
        "snapshot_id": "1629574252",
        "altitude": "23500",
        "heading": "213",
        "latitude": "25.44871",
        "longitude": "62.60347",
        "radar_id": "41051",
        "speed": "352",
        "squawk": "0442"
    },
    {
        "snapshot_id": "1629574313",
        "altitude": "24050",
        "heading": "223",
        "latitude": "25.36822",
        "longitude": "62.53957",
        "radar_id": "41051",
        "speed": "332",
        "squawk": "0442"
    },
    {
        "snapshot_id": "1629574314",
        "altitude": "24050",
        "heading": "223",
        "latitude": "25.36753",
        "longitude": "62.53905",
        "radar_id": "42251",
        "speed": "331",
        "squawk": "0442"
    },
    {
        "snapshot_id": "1629574316",
        "altitude": "24100",
        "heading": "225",
        "latitude": "25.36496",
        "longitude": "62.53596",
        "radar_id": "41051",
        "speed": "329",
        "squawk": "0442"
    },
    {
        "snapshot_id": "1629574317",
        "altitude": "24125",
        "heading": "225",
        "latitude": "25.36436",
        "longitude": "62.53555",
        "radar_id": "42251",
        "speed": "329",
        "squawk": "0442"
    },
    {
        "snapshot_id": "1629574320",
        "altitude": "24175",
        "heading": "226",
        "latitude": "25.36133",
        "longitude": "62.53200",
        "radar_id": "41051",
        "speed": "327",
        "squawk": "0442"
    },
    {
        "snapshot_id": "1629574323",
        "altitude": "24225",
        "heading": "227",
        "latitude": "25.35841",
        "longitude": "62.52843",
        "radar_id": "41051",
        "speed": "325",
        "squawk": "0442"
    },
    {
        "snapshot_id": "1629574325",
        "altitude": "24300",
        "heading": "229",
        "latitude": "25.35552",
        "longitude": "62.52480",
        "radar_id": "41051",
        "speed": "323",
        "squawk": "0442"
    },
    {
        "snapshot_id": "1629574326",
        "altitude": "24300",
        "heading": "229",
        "latitude": "25.35494",
        "longitude": "62.52406",
        "radar_id": "42251",
        "speed": "323",
        "squawk": "0442"
    },
    {
        "snapshot_id": "1629574328",
        "altitude": "24325",
        "heading": "230",
        "latitude": "25.35306",
        "longitude": "62.52167",
        "radar_id": "41051",
        "speed": "322",
        "squawk": "0442"
    },
    {
        "snapshot_id": "1629574331",
        "altitude": "24375",
        "heading": "230",
        "latitude": "25.35030",
        "longitude": "62.51806",
        "radar_id": "41051",
        "speed": "321",
        "squawk": "0442"
    },
    {
        "snapshot_id": "1629574393",
        "altitude": "25300",
        "heading": "230",
        "latitude": "25.29406",
        "longitude": "62.44261",
        "radar_id": "41051",
        "speed": "302",
        "squawk": "0442"
    },
    {
        "snapshot_id": "1629574454",
        "altitude": "25525",
        "heading": "230",
        "latitude": "25.23839",
        "longitude": "62.36750",
        "radar_id": "42251",
        "speed": "312",
        "squawk": "0442"
    },
    {
        "snapshot_id": "1629574517",
        "altitude": "25500",
        "heading": "230",
        "latitude": "25.18052",
        "longitude": "62.28973",
        "radar_id": "42251",
        "speed": "326",
        "squawk": "0442"
    },
    {
        "snapshot_id": "1629574580",
        "altitude": "25500",
        "heading": "230",
        "latitude": "25.11908",
        "longitude": "62.20734",
        "radar_id": "41051",
        "speed": "334",
        "squawk": "0442"
    },
    {
        "snapshot_id": "1629574641",
        "altitude": "25500",
        "heading": "230",
        "latitude": "25.05832",
        "longitude": "62.12598",
        "radar_id": "41051",
        "speed": "340",
        "squawk": "0442"
    },
    {
        "snapshot_id": "1629574702",
        "altitude": "25500",
        "heading": "230",
        "latitude": "24.99655",
        "longitude": "62.04332",
        "radar_id": "41051",
        "speed": "341",
        "squawk": "0442"
    },
    {
        "snapshot_id": "1629574764",
        "altitude": "25500",
        "heading": "230",
        "latitude": "24.93477",
        "longitude": "61.96071",
        "radar_id": "41051",
        "speed": "343",
        "squawk": "0442"
    },
    {
        "snapshot_id": "1629574830",
        "altitude": "25500",
        "heading": "230",
        "latitude": "24.86746",
        "longitude": "61.87096",
        "radar_id": "41051",
        "speed": "343",
        "squawk": "0442"
    },
    {
        "snapshot_id": "1629574892",
        "altitude": "25500",
        "heading": "230",
        "latitude": "24.80494",
        "longitude": "61.78778",
        "radar_id": "41051",
        "speed": "343",
        "squawk": "0442"
    },
    {
        "snapshot_id": "1629574953",
        "altitude": "25500",
        "heading": "230",
        "latitude": "24.74321",
        "longitude": "61.70580",
        "radar_id": "41051",
        "speed": "343",
        "squawk": "0442"
    },
    {
        "snapshot_id": "1629575023",
        "altitude": "25500",
        "heading": "230",
        "latitude": "24.67126",
        "longitude": "61.61072",
        "radar_id": "41051",
        "speed": "346",
        "squawk": "0442"
    },
    {
        "snapshot_id": "1629575084",
        "altitude": "25500",
        "heading": "230",
        "latitude": "24.60928",
        "longitude": "61.52730",
        "radar_id": "41051",
        "speed": "347",
        "squawk": "0442"
    },
    {
        "snapshot_id": "1629575158",
        "altitude": "25500",
        "heading": "218",
        "latitude": "24.53133",
        "longitude": "61.43051",
        "radar_id": "41051",
        "speed": "345",
        "squawk": "0442"
    },
    {
        "snapshot_id": "1629575161",
        "altitude": "25500",
        "heading": "217",
        "latitude": "24.52800",
        "longitude": "61.42767",
        "radar_id": "41051",
        "speed": "345",
        "squawk": "0442"
    },
    {
        "snapshot_id": "1629575164",
        "altitude": "25500",
        "heading": "214",
        "latitude": "24.52373",
        "longitude": "61.42426",
        "radar_id": "41051",
        "speed": "345",
        "squawk": "0442"
    },
    {
        "snapshot_id": "1629575170",
        "altitude": "25500",
        "heading": "213",
        "latitude": "24.51549",
        "longitude": "61.41826",
        "radar_id": "41051",
        "speed": "344",
        "squawk": "0442"
    },
    {
        "snapshot_id": "1629575271",
        "altitude": "25500",
        "heading": "253",
        "latitude": "24.39560",
        "longitude": "61.30626",
        "radar_id": "41051",
        "speed": "345",
        "squawk": "0442"
    },
    {
        "snapshot_id": "1629575274",
        "altitude": "25500",
        "heading": "254",
        "latitude": "24.39426",
        "longitude": "61.30117",
        "radar_id": "41051",
        "speed": "345",
        "squawk": "0442"
    },
    {
        "snapshot_id": "1629575277",
        "altitude": "25525",
        "heading": "255",
        "latitude": "24.39285",
        "longitude": "61.29578",
        "radar_id": "41051",
        "speed": "344",
        "squawk": "0442"
    },
    {
        "snapshot_id": "1629575357",
        "altitude": "25675",
        "heading": "257",
        "latitude": "24.36438",
        "longitude": "61.15992",
        "radar_id": "41051",
        "speed": "339",
        "squawk": "0442"
    },
    {
        "snapshot_id": "1629575417",
        "altitude": "25975",
        "heading": "257",
        "latitude": "24.34379",
        "longitude": "61.06113",
        "radar_id": "41051",
        "speed": "334",
        "squawk": "4071"
    },
    {
        "snapshot_id": "1629575486",
        "altitude": "26025",
        "heading": "257",
        "latitude": "24.31977",
        "longitude": "60.94655",
        "radar_id": "41051",
        "speed": "338",
        "squawk": "4071"
    },
    {
        "snapshot_id": "1629575519",
        "altitude": "26000",
        "heading": "256",
        "latitude": "24.30790",
        "longitude": "60.88986",
        "radar_id": "41051",
        "speed": "340",
        "squawk": "4071"
    },
    {
        "snapshot_id": "1629575595",
        "altitude": "26000",
        "heading": "256",
        "latitude": "24.28111",
        "longitude": "60.76233",
        "radar_id": "41051",
        "speed": "343",
        "squawk": "4071"
    },
    {
        "snapshot_id": "1629575642",
        "altitude": "26000",
        "heading": "257",
        "latitude": "24.26431",
        "longitude": "60.68319",
        "radar_id": "41051",
        "speed": "341",
        "squawk": "4071"
    },
    {
        "snapshot_id": "1629575731",
        "altitude": "26000",
        "heading": "256",
        "latitude": "24.23236",
        "longitude": "60.53238",
        "radar_id": "3161",
        "speed": "341",
        "squawk": "4071"
    },
    {
        "snapshot_id": "1629575787",
        "altitude": "26000",
        "heading": "256",
        "latitude": "24.21263",
        "longitude": "60.43925",
        "radar_id": "3161",
        "speed": "341",
        "squawk": "4071"
    },
    {
        "snapshot_id": "1629575838",
        "altitude": "26000",
        "heading": "256",
        "latitude": "24.19408",
        "longitude": "60.35267",
        "radar_id": "3161",
        "speed": "341",
        "squawk": "4071"
    },
    {
        "snapshot_id": "1629575920",
        "altitude": "25975",
        "heading": "256",
        "latitude": "24.16438",
        "longitude": "60.21430",
        "radar_id": "41575",
        "speed": "342",
        "squawk": "4071"
    },
    {
        "snapshot_id": "1629576006",
        "altitude": "26000",
        "heading": "256",
        "latitude": "24.13348",
        "longitude": "60.07090",
        "radar_id": "40021",
        "speed": "342",
        "squawk": "4071"
    },
    {
        "snapshot_id": "1629576069",
        "altitude": "26000",
        "heading": "256",
        "latitude": "24.11052",
        "longitude": "59.96426",
        "radar_id": "3161",
        "speed": "342",
        "squawk": "4071"
    },
    {
        "snapshot_id": "1629576132",
        "altitude": "26000",
        "heading": "256",
        "latitude": "24.08766",
        "longitude": "59.85906",
        "radar_id": "42251",
        "speed": "341",
        "squawk": "4071"
    },
    {
        "snapshot_id": "1629576193",
        "altitude": "26000",
        "heading": "256",
        "latitude": "24.06499",
        "longitude": "59.75562",
        "radar_id": "42251",
        "speed": "341",
        "squawk": "4071"
    },
    {
        "snapshot_id": "1629576259",
        "altitude": "26000",
        "heading": "256",
        "latitude": "24.04079",
        "longitude": "59.64482",
        "radar_id": "41051",
        "speed": "341",
        "squawk": "4071"
    },
    {
        "snapshot_id": "1629576322",
        "altitude": "26000",
        "heading": "256",
        "latitude": "24.01744",
        "longitude": "59.53857",
        "radar_id": "42251",
        "speed": "340",
        "squawk": "4071"
    },
    {
        "snapshot_id": "1629576384",
        "altitude": "25975",
        "heading": "256",
        "latitude": "23.99497",
        "longitude": "59.43634",
        "radar_id": "40021",
        "speed": "340",
        "squawk": "4071"
    },
    {
        "snapshot_id": "1629576444",
        "altitude": "26000",
        "heading": "256",
        "latitude": "23.97281",
        "longitude": "59.33624",
        "radar_id": "41821",
        "speed": "340",
        "squawk": "4071"
    },
    {
        "snapshot_id": "1629576506",
        "altitude": "26000",
        "heading": "256",
        "latitude": "23.94978",
        "longitude": "59.23223",
        "radar_id": "41821",
        "speed": "341",
        "squawk": "4071"
    },
    {
        "snapshot_id": "1629576562",
        "altitude": "25975",
        "heading": "271",
        "latitude": "23.93288",
        "longitude": "59.13800",
        "radar_id": "41821",
        "speed": "341",
        "squawk": "4071"
    },
    {
        "snapshot_id": "1629576563",
        "altitude": "25975",
        "heading": "271",
        "latitude": "23.93285",
        "longitude": "59.13732",
        "radar_id": "41575",
        "speed": "341",
        "squawk": "4071"
    },
    {
        "snapshot_id": "1629576566",
        "altitude": "25975",
        "heading": "274",
        "latitude": "23.93302",
        "longitude": "59.13205",
        "radar_id": "41821",
        "speed": "339",
        "squawk": "4071"
    },
    {
        "snapshot_id": "1629576572",
        "altitude": "25975",
        "heading": "280",
        "latitude": "23.93446",
        "longitude": "59.12116",
        "radar_id": "41821",
        "speed": "338",
        "squawk": "4071"
    },
    {
        "snapshot_id": "1629576574",
        "altitude": "25975",
        "heading": "283",
        "latitude": "23.93532",
        "longitude": "59.11708",
        "radar_id": "41575",
        "speed": "337",
        "squawk": "4071"
    },
    {
        "snapshot_id": "1629576575",
        "altitude": "25975",
        "heading": "283",
        "latitude": "23.93550",
        "longitude": "59.11621",
        "radar_id": "41821",
        "speed": "337",
        "squawk": "4071"
    },
    {
        "snapshot_id": "1629576578",
        "altitude": "25975",
        "heading": "285",
        "latitude": "23.93688",
        "longitude": "59.11054",
        "radar_id": "41821",
        "speed": "336",
        "squawk": "4071"
    },
    {
        "snapshot_id": "1629576583",
        "altitude": "26000",
        "heading": "287",
        "latitude": "23.93874",
        "longitude": "59.10463",
        "radar_id": "42251",
        "speed": "336",
        "squawk": "4071"
    },
    {
        "snapshot_id": "1629576592",
        "altitude": "26000",
        "heading": "288",
        "latitude": "23.94335",
        "longitude": "59.08950",
        "radar_id": "41821",
        "speed": "335",
        "squawk": "4071"
    },
    {
        "snapshot_id": "1629576654",
        "altitude": "26000",
        "heading": "289",
        "latitude": "23.97547",
        "longitude": "58.98933",
        "radar_id": "41821",
        "speed": "337",
        "squawk": "4071"
    },
    {
        "snapshot_id": "1629576716",
        "altitude": "25975",
        "heading": "288",
        "latitude": "24.00741",
        "longitude": "58.88926",
        "radar_id": "41821",
        "speed": "338",
        "squawk": "4071"
    },
    {
        "snapshot_id": "1629576776",
        "altitude": "26025",
        "heading": "288",
        "latitude": "24.03813",
        "longitude": "58.79209",
        "radar_id": "41575",
        "speed": "336",
        "squawk": "4071"
    },
    {
        "snapshot_id": "1629576839",
        "altitude": "25975",
        "heading": "288",
        "latitude": "24.07008",
        "longitude": "58.69166",
        "radar_id": "41051",
        "speed": "337",
        "squawk": "4071"
    },
    {
        "snapshot_id": "1629576900",
        "altitude": "26000",
        "heading": "289",
        "latitude": "24.10093",
        "longitude": "58.59340",
        "radar_id": "41821",
        "speed": "336",
        "squawk": "4071"
    },
    {
        "snapshot_id": "1629576963",
        "altitude": "26000",
        "heading": "289",
        "latitude": "24.13338",
        "longitude": "58.49126",
        "radar_id": "40150",
        "speed": "335",
        "squawk": "4071"
    },
    {
        "snapshot_id": "1629577026",
        "altitude": "26000",
        "heading": "289",
        "latitude": "24.16502",
        "longitude": "58.39213",
        "radar_id": "41051",
        "speed": "333",
        "squawk": "4071"
    },
    {
        "snapshot_id": "1629577086",
        "altitude": "26000",
        "heading": "289",
        "latitude": "24.19571",
        "longitude": "58.29496",
        "radar_id": "40021",
        "speed": "334",
        "squawk": "4071"
    },
    {
        "snapshot_id": "1629577148",
        "altitude": "25975",
        "heading": "288",
        "latitude": "24.22696",
        "longitude": "58.19585",
        "radar_id": "41821",
        "speed": "336",
        "squawk": "4071"
    },
    {
        "snapshot_id": "1629577211",
        "altitude": "26000",
        "heading": "288",
        "latitude": "24.25873",
        "longitude": "58.09524",
        "radar_id": "40150",
        "speed": "336",
        "squawk": "4071"
    },
    {
        "snapshot_id": "1629577275",
        "altitude": "26000",
        "heading": "288",
        "latitude": "24.29082",
        "longitude": "57.99266",
        "radar_id": "40150",
        "speed": "337",
        "squawk": "4071"
    },
    {
        "snapshot_id": "1629577335",
        "altitude": "26000",
        "heading": "288",
        "latitude": "24.32154",
        "longitude": "57.89463",
        "radar_id": "40150",
        "speed": "337",
        "squawk": "4071"
    },
    {
        "snapshot_id": "1629577405",
        "altitude": "26000",
        "heading": "288",
        "latitude": "24.35674",
        "longitude": "57.78254",
        "radar_id": "41575",
        "speed": "337",
        "squawk": "4071"
    },
    {
        "snapshot_id": "1629577466",
        "altitude": "26000",
        "heading": "288",
        "latitude": "24.38709",
        "longitude": "57.68465",
        "radar_id": "41575",
        "speed": "336",
        "squawk": "4071"
    },
    {
        "snapshot_id": "1629577532",
        "altitude": "26000",
        "heading": "288",
        "latitude": "24.42041",
        "longitude": "57.57787",
        "radar_id": "836",
        "speed": "334",
        "squawk": "4071"
    },
    {
        "snapshot_id": "1629577595",
        "altitude": "26000",
        "heading": "288",
        "latitude": "24.45184",
        "longitude": "57.47617",
        "radar_id": "40150",
        "speed": "333",
        "squawk": "4071"
    },
    {
        "snapshot_id": "1629577657",
        "altitude": "25950",
        "heading": "288",
        "latitude": "24.48203",
        "longitude": "57.37803",
        "radar_id": "40021",
        "speed": "335",
        "squawk": "4071"
    },
    {
        "snapshot_id": "1629577719",
        "altitude": "24400",
        "heading": "287",
        "latitude": "24.51380",
        "longitude": "57.27401",
        "radar_id": "41821",
        "speed": "359",
        "squawk": "4071"
    },
    {
        "snapshot_id": "1629577780",
        "altitude": "22600",
        "heading": "288",
        "latitude": "24.54588",
        "longitude": "57.16827",
        "radar_id": "40150",
        "speed": "359",
        "squawk": "4071"
    },
    {
        "snapshot_id": "1629577845",
        "altitude": "20700",
        "heading": "288",
        "latitude": "24.58042",
        "longitude": "57.05454",
        "radar_id": "5430",
        "speed": "351",
        "squawk": "4071"
    },
    {
        "snapshot_id": "1629577911",
        "altitude": "19025",
        "heading": "287",
        "latitude": "24.61368",
        "longitude": "56.94717",
        "radar_id": "40021",
        "speed": "318",
        "squawk": "4071"
    },
    {
        "snapshot_id": "1629577972",
        "altitude": "19000",
        "heading": "285",
        "latitude": "24.64154",
        "longitude": "56.85352",
        "radar_id": "40021",
        "speed": "328",
        "squawk": "4071"
    },
    {
        "snapshot_id": "1629578036",
        "altitude": "19000",
        "heading": "279",
        "latitude": "24.65868",
        "longitude": "56.74642",
        "radar_id": "836",
        "speed": "334",
        "squawk": "4071"
    },
    {
        "snapshot_id": "1629578097",
        "altitude": "18975",
        "heading": "277",
        "latitude": "24.67204",
        "longitude": "56.64653",
        "radar_id": "41821",
        "speed": "322",
        "squawk": "4071"
    },
    {
        "snapshot_id": "1629578158",
        "altitude": "17650",
        "heading": "278",
        "latitude": "24.68614",
        "longitude": "56.54521",
        "radar_id": "836",
        "speed": "330",
        "squawk": "4071"
    },
    {
        "snapshot_id": "1629578188",
        "altitude": "16800",
        "heading": "278",
        "latitude": "24.69266",
        "longitude": "56.49569",
        "radar_id": "836",
        "speed": "322",
        "squawk": "4071"
    },
    {
        "snapshot_id": "1629578219",
        "altitude": "15925",
        "heading": "278",
        "latitude": "24.69918",
        "longitude": "56.44568",
        "radar_id": "836",
        "speed": "315",
        "squawk": "4071"
    },
    {
        "snapshot_id": "1629578259",
        "altitude": "15075",
        "heading": "277",
        "latitude": "24.70723",
        "longitude": "56.38406",
        "radar_id": "836",
        "speed": "309",
        "squawk": "4071"
    },
    {
        "snapshot_id": "1629578293",
        "altitude": "15000",
        "heading": "278",
        "latitude": "24.71443",
        "longitude": "56.33072",
        "radar_id": "40021",
        "speed": "302",
        "squawk": "4071"
    },
    {
        "snapshot_id": "1629578323",
        "altitude": "14600",
        "heading": "296",
        "latitude": "24.72633",
        "longitude": "56.28611",
        "radar_id": "40021",
        "speed": "305",
        "squawk": "4071"
    },
    {
        "snapshot_id": "1629578330",
        "altitude": "14400",
        "heading": "299",
        "latitude": "24.73083",
        "longitude": "56.27710",
        "radar_id": "41821",
        "speed": "305",
        "squawk": "4071"
    },
    {
        "snapshot_id": "1629578333",
        "altitude": "14325",
        "heading": "300",
        "latitude": "24.73306",
        "longitude": "56.27299",
        "radar_id": "41821",
        "speed": "304",
        "squawk": "4071"
    },
    {
        "snapshot_id": "1629578343",
        "altitude": "14050",
        "heading": "299",
        "latitude": "24.73993",
        "longitude": "56.25977",
        "radar_id": "41821",
        "speed": "302",
        "squawk": "4071"
    },
    {
        "snapshot_id": "1629578384",
        "altitude": "12875",
        "heading": "298",
        "latitude": "24.76771",
        "longitude": "56.20560",
        "radar_id": "40021",
        "speed": "297",
        "squawk": "4071"
    },
    {
        "snapshot_id": "1629578422",
        "altitude": "12275",
        "heading": "299",
        "latitude": "24.79312",
        "longitude": "56.15688",
        "radar_id": "41821",
        "speed": "282",
        "squawk": "4071"
    },
    {
        "snapshot_id": "1629578463",
        "altitude": "11275",
        "heading": "299",
        "latitude": "24.81990",
        "longitude": "56.10550",
        "radar_id": "836",
        "speed": "277",
        "squawk": "4071"
    },
    {
        "snapshot_id": "1629578475",
        "altitude": "10975",
        "heading": "299",
        "latitude": "24.82727",
        "longitude": "56.09111",
        "radar_id": "40021",
        "speed": "275",
        "squawk": "4071"
    },
    {
        "snapshot_id": "1629578487",
        "altitude": "10675",
        "heading": "297",
        "latitude": "24.83482",
        "longitude": "56.07630",
        "radar_id": "40021",
        "speed": "274",
        "squawk": "4071"
    },
    {
        "snapshot_id": "1629578506",
        "altitude": "10350",
        "heading": "290",
        "latitude": "24.84353",
        "longitude": "56.05214",
        "radar_id": "836",
        "speed": "270",
        "squawk": "4071"
    },
    {
        "snapshot_id": "1629578517",
        "altitude": "10300",
        "heading": "290",
        "latitude": "24.84869",
        "longitude": "56.03739",
        "radar_id": "41821",
        "speed": "268",
        "squawk": "4071"
    },
    {
        "snapshot_id": "1629578530",
        "altitude": "10275",
        "heading": "290",
        "latitude": "24.85387",
        "longitude": "56.02203",
        "radar_id": "40021",
        "speed": "268",
        "squawk": "4071"
    },
    {
        "snapshot_id": "1629578543",
        "altitude": "10275",
        "heading": "290",
        "latitude": "24.85969",
        "longitude": "56.00529",
        "radar_id": "836",
        "speed": "267",
        "squawk": "4071"
    },
    {
        "snapshot_id": "1629578561",
        "altitude": "10275",
        "heading": "290",
        "latitude": "24.86741",
        "longitude": "55.98275",
        "radar_id": "836",
        "speed": "261",
        "squawk": "4071"
    },
    {
        "snapshot_id": "1629578572",
        "altitude": "10050",
        "heading": "290",
        "latitude": "24.87207",
        "longitude": "55.96881",
        "radar_id": "40021",
        "speed": "260",
        "squawk": "4071"
    },
    {
        "snapshot_id": "1629578584",
        "altitude": "9775",
        "heading": "290",
        "latitude": "24.87719",
        "longitude": "55.95363",
        "radar_id": "40021",
        "speed": "262",
        "squawk": "4071"
    },
    {
        "snapshot_id": "1629578596",
        "altitude": "9475",
        "heading": "290",
        "latitude": "24.88268",
        "longitude": "55.93798",
        "radar_id": "41821",
        "speed": "264",
        "squawk": "4071"
    },
    {
        "snapshot_id": "1629578629",
        "altitude": "8650",
        "heading": "291",
        "latitude": "24.89726",
        "longitude": "55.89645",
        "radar_id": "41821",
        "speed": "269",
        "squawk": "4071"
    },
    {
        "snapshot_id": "1629578642",
        "altitude": "8350",
        "heading": "291",
        "latitude": "24.90330",
        "longitude": "55.87957",
        "radar_id": "41821",
        "speed": "268",
        "squawk": "4071"
    },
    {
        "snapshot_id": "1629578652",
        "altitude": "8125",
        "heading": "291",
        "latitude": "24.90777",
        "longitude": "55.86729",
        "radar_id": "41821",
        "speed": "269",
        "squawk": "4071"
    },
    {
        "snapshot_id": "1629578700",
        "altitude": "6925",
        "heading": "291",
        "latitude": "24.93041",
        "longitude": "55.80566",
        "radar_id": "836",
        "speed": "272",
        "squawk": "4071"
    },
    {
        "snapshot_id": "1629578707",
        "altitude": "6750",
        "heading": "291",
        "latitude": "24.93370",
        "longitude": "55.79666",
        "radar_id": "836",
        "speed": "272",
        "squawk": "4071"
    },
    {
        "snapshot_id": "1629578771",
        "altitude": "4850",
        "heading": "299",
        "latitude": "24.96941",
        "longitude": "55.71981",
        "radar_id": "6456",
        "speed": "252",
        "squawk": "4071"
    },
    {
        "snapshot_id": "1629578791",
        "altitude": "4325",
        "heading": "298",
        "latitude": "24.98072",
        "longitude": "55.69747",
        "radar_id": "6456",
        "speed": "239",
        "squawk": "4071"
    },
    {
        "snapshot_id": "1629578805",
        "altitude": "3950",
        "heading": "293",
        "latitude": "24.98775",
        "longitude": "55.68224",
        "radar_id": "42438",
        "speed": "232",
        "squawk": "4071"
    },
    {
        "snapshot_id": "1629578811",
        "altitude": "3825",
        "heading": "293",
        "latitude": "24.98999",
        "longitude": "55.67602",
        "radar_id": "5211",
        "speed": "227",
        "squawk": "4071"
    },
    {
        "snapshot_id": "1629578834",
        "altitude": "3300",
        "heading": "298",
        "latitude": "25.00099",
        "longitude": "55.65338",
        "radar_id": "11020",
        "speed": "215",
        "squawk": "4071"
    },
    {
        "snapshot_id": "1629578840",
        "altitude": "3125",
        "heading": "298",
        "latitude": "25.00390",
        "longitude": "55.64736",
        "radar_id": "42438",
        "speed": "213",
        "squawk": "4071"
    },
    {
        "snapshot_id": "1629578848",
        "altitude": "2950",
        "heading": "298",
        "latitude": "25.00731",
        "longitude": "55.64036",
        "radar_id": "42438",
        "speed": "210",
        "squawk": "4071"
    },
    {
        "snapshot_id": "1629578875",
        "altitude": "2750",
        "heading": "299",
        "latitude": "25.01950",
        "longitude": "55.61632",
        "radar_id": "11020",
        "speed": "188",
        "squawk": "4071"
    },
    {
        "snapshot_id": "1629578879",
        "altitude": "2750",
        "heading": "299",
        "latitude": "25.02123",
        "longitude": "55.61274",
        "radar_id": "42438",
        "speed": "185",
        "squawk": "4071"
    },
    {
        "snapshot_id": "1629578901",
        "altitude": "2800",
        "heading": "269",
        "latitude": "25.02635",
        "longitude": "55.59367",
        "radar_id": "6456",
        "speed": "174",
        "squawk": "4071"
    },
    {
        "snapshot_id": "1629578915",
        "altitude": "2800",
        "heading": "261",
        "latitude": "25.02513",
        "longitude": "55.58201",
        "radar_id": "6456",
        "speed": "181",
        "squawk": "4071"
    },
    {
        "snapshot_id": "1629578925",
        "altitude": "2775",
        "heading": "261",
        "latitude": "25.02374",
        "longitude": "55.57253",
        "radar_id": "6456",
        "speed": "182",
        "squawk": "4071"
    },
    {
        "snapshot_id": "1629578942",
        "altitude": "2750",
        "heading": "264",
        "latitude": "25.02150",
        "longitude": "55.55636",
        "radar_id": "6456",
        "speed": "177",
        "squawk": "4071"
    },
    {
        "snapshot_id": "1629578951",
        "altitude": "2750",
        "heading": "275",
        "latitude": "25.02154",
        "longitude": "55.54850",
        "radar_id": "6456",
        "speed": "175",
        "squawk": "4071"
    },
    {
        "snapshot_id": "1629578953",
        "altitude": "2750",
        "heading": "277",
        "latitude": "25.02173",
        "longitude": "55.54713",
        "radar_id": "6456",
        "speed": "175",
        "squawk": "4071"
    },
    {
        "snapshot_id": "1629578955",
        "altitude": "2775",
        "heading": "277",
        "latitude": "25.02191",
        "longitude": "55.54489",
        "radar_id": "6456",
        "speed": "174",
        "squawk": "4071"
    },
    {
        "snapshot_id": "1629578966",
        "altitude": "2775",
        "heading": "277",
        "latitude": "25.02310",
        "longitude": "55.53599",
        "radar_id": "6456",
        "speed": "172",
        "squawk": "4071"
    },
    {
        "snapshot_id": "1629578977",
        "altitude": "2800",
        "heading": "277",
        "latitude": "25.02430",
        "longitude": "55.52640",
        "radar_id": "6456",
        "speed": "164",
        "squawk": "4071"
    },
    {
        "snapshot_id": "1629578987",
        "altitude": "2850",
        "heading": "278",
        "latitude": "25.02532",
        "longitude": "55.51796",
        "radar_id": "6456",
        "speed": "156",
        "squawk": "4071"
    },
    {
        "snapshot_id": "1629578996",
        "altitude": "2650",
        "heading": "276",
        "latitude": "25.02617",
        "longitude": "55.51097",
        "radar_id": "6456",
        "speed": "149",
        "squawk": "4071"
    },
    {
        "snapshot_id": "1629579007",
        "altitude": "2825",
        "heading": "271",
        "latitude": "25.02653",
        "longitude": "55.50324",
        "radar_id": "6456",
        "speed": "149",
        "squawk": "4071"
    },
    {
        "snapshot_id": "1629579009",
        "altitude": "2850",
        "heading": "271",
        "latitude": "25.02653",
        "longitude": "55.50132",
        "radar_id": "6456",
        "speed": "150",
        "squawk": "4071"
    },
    {
        "snapshot_id": "1629579017",
        "altitude": "2800",
        "heading": "271",
        "latitude": "25.02667",
        "longitude": "55.49531",
        "radar_id": "6456",
        "speed": "153",
        "squawk": "4071"
    },
    {
        "snapshot_id": "1629579018",
        "altitude": "2775",
        "heading": "271",
        "latitude": "25.02667",
        "longitude": "55.49464",
        "radar_id": "6456",
        "speed": "154",
        "squawk": "4071"
    },
    {
        "snapshot_id": "1629579022",
        "altitude": "2700",
        "heading": "271",
        "latitude": "25.02667",
        "longitude": "55.49133",
        "radar_id": "6456",
        "speed": "155",
        "squawk": "4071"
    },
    {
        "snapshot_id": "1629579031",
        "altitude": "2525",
        "heading": "271",
        "latitude": "25.02704",
        "longitude": "55.48431",
        "radar_id": "23292",
        "speed": "150",
        "squawk": "4071"
    },
    {
        "snapshot_id": "1629579041",
        "altitude": "2325",
        "heading": "270",
        "latitude": "25.02704",
        "longitude": "55.47638",
        "radar_id": "23292",
        "speed": "147",
        "squawk": "4071"
    },
    {
        "snapshot_id": "1629579069",
        "altitude": "1850",
        "heading": "268",
        "latitude": "25.02704",
        "longitude": "55.45583",
        "radar_id": "23292",
        "speed": "148",
        "squawk": "4071"
    },
    {
        "snapshot_id": "1629579080",
        "altitude": "1650",
        "heading": "268",
        "latitude": "25.02686",
        "longitude": "55.44758",
        "radar_id": "42438",
        "speed": "150",
        "squawk": "4071"
    },
    {
        "snapshot_id": "1629579092",
        "altitude": "1400",
        "heading": "273",
        "latitude": "25.02704",
        "longitude": "55.43782",
        "radar_id": "41219",
        "speed": "151",
        "squawk": "4071"
    },
    {
        "snapshot_id": "1629579101",
        "altitude": "1250",
        "heading": "273",
        "latitude": "25.02736",
        "longitude": "55.43162",
        "radar_id": "41219",
        "speed": "150",
        "squawk": "4071"
    },
    {
        "snapshot_id": "1629579119",
        "altitude": "975",
        "heading": "269",
        "latitude": "25.02754",
        "longitude": "55.41855",
        "radar_id": "42438",
        "speed": "137",
        "squawk": "4071"
    },
    {
        "snapshot_id": "1629579138",
        "altitude": "800",
        "heading": "268",
        "latitude": "25.02718",
        "longitude": "55.40550",
        "radar_id": "42438",
        "speed": "136",
        "squawk": "4071"
    },
    {
        "snapshot_id": "1629579141",
        "altitude": "750",
        "heading": "268",
        "latitude": "25.02718",
        "longitude": "55.40291",
        "radar_id": "42438",
        "speed": "138",
        "squawk": "4071"
    },
    {
        "snapshot_id": "1629579153",
        "altitude": "600",
        "heading": "269",
        "latitude": "25.02718",
        "longitude": "55.39457",
        "radar_id": "14589",
        "speed": "137",
        "squawk": "4071"
    },
    {
        "snapshot_id": "1629579164",
        "altitude": "500",
        "heading": "269",
        "latitude": "25.02704",
        "longitude": "55.38717",
        "radar_id": "42438",
        "speed": "134",
        "squawk": "4071"
    },
    {
        "snapshot_id": "1629579175",
        "altitude": "400",
        "heading": "269",
        "latitude": "25.02704",
        "longitude": "55.37979",
        "radar_id": "42438",
        "speed": "130",
        "squawk": "4071"
    }
]